[{"path":"C:\\Users\\bojan\\.m2\\repository\\org\\mule\\modules\\mule-scripting-module\\2.0.0\\mule-scripting-module-2.0.0-mule-plugin.jar","restricted":false},{"path":"C:\\Users\\bojan\\.m2\\repository\\org\\mule\\modules\\mule-scripting-module\\2.0.0\\mule-scripting-module-2.0.0-mule-plugin.jar","restricted":false},{"path":"C:\\Users\\bojan\\.m2\\repository\\io\\projectreactor\\reactor-core\\3.3.6.RELEASE\\reactor-core-3.3.6.RELEASE.jar","restricted":false},{"path":"C:\\Users\\bojan\\.m2\\repository\\org\\mule\\tests\\mule-tests-model\\4.2.0\\mule-tests-model-4.2.0.jar","restricted":false}]